README.txt
setup.py
bitevery/__init__.py
bitevery/apiCode.py
bitevery/apiUtil.py
bitevery/tip.py
bitevery.egg-info/PKG-INFO
bitevery.egg-info/SOURCES.txt
bitevery.egg-info/dependency_links.txt
bitevery.egg-info/not-zip-safe
bitevery.egg-info/top_level.txt