Metadata-Version: 1.0
Name: bitevery
Version: 0.0.1b3
Summary: BitEvery Python API
Home-page: https://www.bitevery.com
Author: BitEvery
Author-email: support@bitevery.com
License: MIT
Platform: UNKNOWN
